README.md
setup.py
ai_lib_ls/__init__.py
ai_lib_ls/data_frame.py
ai_lib_ls/multi_linear_regression.py
ai_lib_ls/print_str.py
ai_lib_ls/pyhon_machine.py
ai_lib_ls.egg-info/PKG-INFO
ai_lib_ls.egg-info/SOURCES.txt
ai_lib_ls.egg-info/dependency_links.txt
ai_lib_ls.egg-info/top_level.txt
ai_lib_ls/pylib/HttpHelper.py
ai_lib_ls/pylib/MapAdressIP.py
ai_lib_ls/pylib/OtherUtil.py
ai_lib_ls/pylib/__init__.py
ai_lib_ls/pylib/cvs_file.py
ai_lib_ls/pylib/day_timed_task.py
ai_lib_ls/pylib/db_sql.py
ai_lib_ls/pylib/decorator_time_task.py
ai_lib_ls/pylib/imge_util.py
ai_lib_ls/pylib/text_analyze/TextAnalyzeEmotion.py
ai_lib_ls/pylib/text_analyze/TextJieba.py
ai_lib_ls/pylib/text_analyze/__init__.py
ai_lib_ls/pylib/text_analyze/wordcloud/TextWordcloud.py
ai_lib_ls/pylib/text_analyze/wordcloud/__init__.py
ai_lib_ls/pylib/text_transalte/TextCut.py
ai_lib_ls/pylib/text_transalte/__init__.py
ai_lib_ls/pylib/text_transalte/deep_translator.py
ai_lib_ls/pylib/text_transalte/deep_translator/__init__.py
ai_lib_ls/pylib/text_transalte/deep_translator/__main__.py
ai_lib_ls/pylib/text_transalte/deep_translator/base.py
ai_lib_ls/pylib/text_transalte/deep_translator/cli.py
ai_lib_ls/pylib/text_transalte/deep_translator/constants.py
ai_lib_ls/pylib/text_transalte/deep_translator/deepl.py
ai_lib_ls/pylib/text_transalte/deep_translator/detection.py
ai_lib_ls/pylib/text_transalte/deep_translator/engines.py
ai_lib_ls/pylib/text_transalte/deep_translator/exceptions.py
ai_lib_ls/pylib/text_transalte/deep_translator/googleutil.py
ai_lib_ls/pylib/text_transalte/deep_translator/libre.py
ai_lib_ls/pylib/text_transalte/deep_translator/linguee.py
ai_lib_ls/pylib/text_transalte/deep_translator/microsoft.py
ai_lib_ls/pylib/text_transalte/deep_translator/mymemory.py
ai_lib_ls/pylib/text_transalte/deep_translator/papago.py
ai_lib_ls/pylib/text_transalte/deep_translator/pons.py
ai_lib_ls/pylib/text_transalte/deep_translator/qcri.py
ai_lib_ls/pylib/text_transalte/deep_translator/validate.py
ai_lib_ls/pylib/text_transalte/deep_translator/yandex.py
ai_lib_ls/pylib/video_converter/__init__.py
ai_lib_ls/pylib/video_converter/_main_video_text.py
