Metadata-Version: 2.1
Name: ai-lib-ls
Version: 0.0.7
Summary: PyPI Tutorial python  封装包
Home-page: https://gitee.com/qaufue/python_lib.git
Author: qaufue
Author-email: qaufue@gmail.com
Classifier: Programming Language :: Python :: 3
Classifier: License :: OSI Approved :: MIT License
Classifier: Operating System :: OS Independent
